os_launchers/__init__.py
os_launchers/_launchers.py
os_launchers/_version.py
os_launchers/constants.py
os_launchers/exceptions.py
os_launchers-0.1.2.dist-info/LICENSE.md
os_launchers-0.1.2.dist-info/METADATA
os_launchers-0.1.2.dist-info/WHEEL
os_launchers-0.1.2.dist-info/top_level.txt
os_launchers-0.1.2.dist-info/RECORD
