Metadata-Version: 2.1
Name: os-launchers
Version: 0.1.2
Summary: Collection of cross-platform launchers, simplifying common OS interactions
Home-page: https://github.com/Eastern-Skill7173/os-launchers
Author: Eastern-Skill7173
Requires-Python: >=3.5
License-File: LICENSE.md
